{
    "total": [
        {
            "id": "61550024093273",
            "count": 0
        },
        {
            "id": "61550088893899",
            "count": 0
        },
        {
            "id": "100000009580166",
            "count": 1
        },
        {
            "id": "100049873911992",
            "count": 0
        },
        {
            "id": "100077066795182",
            "count": 0
        },
        {
            "id": "100090292607208",
            "count": 2
        },
        {
            "id": "100090462717737",
            "count": 0
        },
        {
            "id": "100090825000753",
            "count": 33
        },
        {
            "id": "100092515583948",
            "count": 0
        },
        {
            "id": "100093551860001",
            "count": 0
        },
        {
            "id": "100094295720287",
            "count": 0
        },
        {
            "id": "100094324782308",
            "count": 0
        },
        {
            "id": "100095657731767",
            "count": 0
        }
    ],
    "week": [
        {
            "id": "61550024093273",
            "count": 0
        },
        {
            "id": "61550088893899",
            "count": 0
        },
        {
            "id": "100000009580166",
            "count": 1
        },
        {
            "id": "100049873911992",
            "count": 0
        },
        {
            "id": "100077066795182",
            "count": 0
        },
        {
            "id": "100090292607208",
            "count": 2
        },
        {
            "id": "100090462717737",
            "count": 0
        },
        {
            "id": "100090825000753",
            "count": 33
        },
        {
            "id": "100092515583948",
            "count": 0
        },
        {
            "id": "100093551860001",
            "count": 0
        },
        {
            "id": "100094295720287",
            "count": 0
        },
        {
            "id": "100094324782308",
            "count": 0
        },
        {
            "id": "100095657731767",
            "count": 0
        }
    ],
    "day": [
        {
            "id": "61550024093273",
            "count": 0,
            "name": "Shan Bé"
        },
        {
            "id": "61550088893899",
            "count": 0,
            "name": "Loli Con"
        },
        {
            "id": "100000009580166",
            "count": 0,
            "name": "Trần Văn Tân"
        },
        {
            "id": "100049873911992",
            "count": 0,
            "name": "Đặng Nguyễn Triều Dâng"
        },
        {
            "id": "100077066795182",
            "count": 0,
            "name": "Abd Lkadr"
        },
        {
            "id": "100090292607208",
            "count": 0,
            "name": "Trieu Dang"
        },
        {
            "id": "100090462717737",
            "count": 0,
            "name": "Emi Fukada"
        },
        {
            "id": "100090825000753",
            "count": 0,
            "name": "Trần Văn Tân"
        },
        {
            "id": "100092515583948",
            "count": 0,
            "name": "Như Quỳnh"
        },
        {
            "id": "100093551860001",
            "count": 0,
            "name": "Hari Nguyễn"
        },
        {
            "id": "100094295720287",
            "count": 0,
            "name": "Bé Miraii"
        },
        {
            "id": "100094324782308",
            "count": 0,
            "name": "Bé Miraii"
        },
        {
            "id": "100095657731767",
            "count": 0,
            "name": "Ne Chann"
        }
    ],
    "time": 5
}